docker_stats
