Metadata-Version: 1.0
Name: docker-stats
Version: 0.0.2
Summary: docker stats, json way
Home-page: https://github.com/mavlyutov/docker-stats
Author: Marat Mavlyutov
Author-email: mavlyutov@yandex-team.ru
License: Apache License, Version 2.0
Platform: UNKNOWN
